{
  "id": "daa5eb68-8ba2-4205-a65a-f1d003c481bc",
  "prevId": "d223179e-62cf-4fe1-98e0-429d7a1a1c77",
  "version": "7",
  "dialect": "postgresql",
  "tables": {
    "public.badge": {
      "name": "badge",
      "schema": "",
      "columns": {
        "id": {
          "name": "id",
          "type": "text",
          "primaryKey": true,
          "notNull": true
        },
        "name": {
          "name": "name",
          "type": "text",
          "primaryKey": false,
          "notNull": true
        },
        "description": {
          "name": "description",
          "type": "text",
          "primaryKey": false,
          "notNull": true
        },
        "valueToComplete": {
          "name": "valueToComplete",
          "type": "integer",
          "primaryKey": false,
          "notNull": true
        },
        "valueName": {
          "name": "valueName",
          "type": "text",
          "primaryKey": false,
          "notNull": true
        },
        "valueDescription": {
          "name": "valueDescription",
          "type": "text",
          "primaryKey": false,
          "notNull": true
        },
        "group": {
          "name": "group",
          "type": "text",
          "primaryKey": false,
          "notNull": true
        },
        "groupWeighting": {
          "name": "groupWeighting",
          "type": "integer",
          "primaryKey": false,
          "notNull": true
        },
        "percentageOfUsersHasBadge": {
          "name": "percentageOfUsersHasBadge",
          "type": "integer",
          "primaryKey": false,
          "notNull": true
        }
      },
      "indexes": {},
      "foreignKeys": {},
      "compositePrimaryKeys": {},
      "uniqueConstraints": {},
      "policies": {},
      "checkConstraints": {},
      "isRLSEnabled": false
    },
    "public.badgeProgress": {
      "name": "badgeProgress",
      "schema": "",
      "columns": {
        "id": {
          "name": "id",
          "type": "uuid",
          "primaryKey": false,
          "notNull": true,
          "default": "gen_random_uuid()"
        },
        "userId": {
          "name": "userId",
          "type": "uuid",
          "primaryKey": false,
          "notNull": true
        },
        "badgeId": {
          "name": "badgeId",
          "type": "text",
          "primaryKey": false,
          "notNull": true
        },
        "completed": {
          "name": "completed",
          "type": "boolean",
          "primaryKey": false,
          "notNull": true
        }
      },
      "indexes": {},
      "foreignKeys": {
        "badgeProgress_userId_user_id_fk": {
          "name": "badgeProgress_userId_user_id_fk",
          "tableFrom": "badgeProgress",
          "tableTo": "user",
          "columnsFrom": [
            "userId"
          ],
          "columnsTo": [
            "id"
          ],
          "onDelete": "cascade",
          "onUpdate": "no action"
        },
        "badgeProgress_badgeId_badge_id_fk": {
          "name": "badgeProgress_badgeId_badge_id_fk",
          "tableFrom": "badgeProgress",
          "tableTo": "badge",
          "columnsFrom": [
            "badgeId"
          ],
          "columnsTo": [
            "id"
          ],
          "onDelete": "cascade",
          "onUpdate": "no action"
        }
      },
      "compositePrimaryKeys": {
        "badgeProgress_userId_badgeId_pk": {
          "name": "badgeProgress_userId_badgeId_pk",
          "columns": [
            "userId",
            "badgeId"
          ]
        }
      },
      "uniqueConstraints": {},
      "policies": {},
      "checkConstraints": {},
      "isRLSEnabled": false
    },
    "public.badgeProgressEvent": {
      "name": "badgeProgressEvent",
      "schema": "",
      "columns": {
        "badgeProgressId": {
          "name": "badgeProgressId",
          "type": "uuid",
          "primaryKey": false,
          "notNull": true
        },
        "timestamp": {
          "name": "timestamp",
          "type": "timestamp",
          "primaryKey": false,
          "notNull": true,
          "default": "now()"
        },
        "value": {
          "name": "value",
          "type": "integer",
          "primaryKey": false,
          "notNull": false
        }
      },
      "indexes": {},
      "foreignKeys": {
        "badgeProgressEvent_badgeProgressId_badgeProgress_id_fk": {
          "name": "badgeProgressEvent_badgeProgressId_badgeProgress_id_fk",
          "tableFrom": "badgeProgressEvent",
          "tableTo": "badgeProgress",
          "columnsFrom": [
            "badgeProgressId"
          ],
          "columnsTo": [
            "id"
          ],
          "onDelete": "cascade",
          "onUpdate": "no action"
        }
      },
      "compositePrimaryKeys": {},
      "uniqueConstraints": {},
      "policies": {},
      "checkConstraints": {},
      "isRLSEnabled": false
    },
    "public.muscle": {
      "name": "muscle",
      "schema": "",
      "columns": {
        "id": {
          "name": "id",
          "type": "uuid",
          "primaryKey": true,
          "notNull": true,
          "default": "gen_random_uuid()"
        },
        "name": {
          "name": "name",
          "type": "text",
          "primaryKey": false,
          "notNull": true
        },
        "latinName": {
          "name": "latinName",
          "type": "text",
          "primaryKey": false,
          "notNull": false
        },
        "muscleGroupId": {
          "name": "muscleGroupId",
          "type": "uuid",
          "primaryKey": false,
          "notNull": true
        },
        "description": {
          "name": "description",
          "type": "text",
          "primaryKey": false,
          "notNull": false
        }
      },
      "indexes": {},
      "foreignKeys": {
        "muscle_muscleGroupId_muscleGroup_id_fk": {
          "name": "muscle_muscleGroupId_muscleGroup_id_fk",
          "tableFrom": "muscle",
          "tableTo": "muscleGroup",
          "columnsFrom": [
            "muscleGroupId"
          ],
          "columnsTo": [
            "id"
          ],
          "onDelete": "cascade",
          "onUpdate": "no action"
        }
      },
      "compositePrimaryKeys": {},
      "uniqueConstraints": {},
      "policies": {},
      "checkConstraints": {},
      "isRLSEnabled": false
    },
    "public.muscleGroup": {
      "name": "muscleGroup",
      "schema": "",
      "columns": {
        "id": {
          "name": "id",
          "type": "uuid",
          "primaryKey": true,
          "notNull": true,
          "default": "gen_random_uuid()"
        },
        "name": {
          "name": "name",
          "type": "text",
          "primaryKey": false,
          "notNull": true
        },
        "description": {
          "name": "description",
          "type": "text",
          "primaryKey": false,
          "notNull": false
        }
      },
      "indexes": {},
      "foreignKeys": {},
      "compositePrimaryKeys": {},
      "uniqueConstraints": {},
      "policies": {},
      "checkConstraints": {},
      "isRLSEnabled": false
    },
    "public.exercise": {
      "name": "exercise",
      "schema": "",
      "columns": {
        "id": {
          "name": "id",
          "type": "uuid",
          "primaryKey": true,
          "notNull": true,
          "default": "gen_random_uuid()"
        },
        "name": {
          "name": "name",
          "type": "text",
          "primaryKey": false,
          "notNull": true
        },
        "description": {
          "name": "description",
          "type": "text",
          "primaryKey": false,
          "notNull": true
        },
        "isPublic": {
          "name": "isPublic",
          "type": "boolean",
          "primaryKey": false,
          "notNull": false
        },
        "userId": {
          "name": "userId",
          "type": "uuid",
          "primaryKey": false,
          "notNull": false
        }
      },
      "indexes": {},
      "foreignKeys": {
        "exercise_userId_user_id_fk": {
          "name": "exercise_userId_user_id_fk",
          "tableFrom": "exercise",
          "tableTo": "user",
          "columnsFrom": [
            "userId"
          ],
          "columnsTo": [
            "id"
          ],
          "onDelete": "set null",
          "onUpdate": "no action"
        }
      },
      "compositePrimaryKeys": {},
      "uniqueConstraints": {},
      "policies": {},
      "checkConstraints": {},
      "isRLSEnabled": false
    },
    "public.exercisePublicRequest": {
      "name": "exercisePublicRequest",
      "schema": "",
      "columns": {
        "id": {
          "name": "id",
          "type": "uuid",
          "primaryKey": true,
          "notNull": true,
          "default": "gen_random_uuid()"
        },
        "execiseId": {
          "name": "execiseId",
          "type": "uuid",
          "primaryKey": false,
          "notNull": true
        },
        "requestMadeAt": {
          "name": "requestMadeAt",
          "type": "timestamp",
          "primaryKey": false,
          "notNull": false,
          "default": "now()"
        }
      },
      "indexes": {},
      "foreignKeys": {
        "exercisePublicRequest_execiseId_exercise_id_fk": {
          "name": "exercisePublicRequest_execiseId_exercise_id_fk",
          "tableFrom": "exercisePublicRequest",
          "tableTo": "exercise",
          "columnsFrom": [
            "execiseId"
          ],
          "columnsTo": [
            "id"
          ],
          "onDelete": "cascade",
          "onUpdate": "no action"
        }
      },
      "compositePrimaryKeys": {},
      "uniqueConstraints": {},
      "policies": {},
      "checkConstraints": {},
      "isRLSEnabled": false
    },
    "public.exerciseToMuscle": {
      "name": "exerciseToMuscle",
      "schema": "",
      "columns": {
        "exercise_id": {
          "name": "exercise_id",
          "type": "uuid",
          "primaryKey": false,
          "notNull": true
        },
        "muscle_id": {
          "name": "muscle_id",
          "type": "uuid",
          "primaryKey": false,
          "notNull": true
        }
      },
      "indexes": {},
      "foreignKeys": {
        "exerciseToMuscle_exercise_id_exercise_id_fk": {
          "name": "exerciseToMuscle_exercise_id_exercise_id_fk",
          "tableFrom": "exerciseToMuscle",
          "tableTo": "exercise",
          "columnsFrom": [
            "exercise_id"
          ],
          "columnsTo": [
            "id"
          ],
          "onDelete": "cascade",
          "onUpdate": "no action"
        },
        "exerciseToMuscle_muscle_id_muscle_id_fk": {
          "name": "exerciseToMuscle_muscle_id_muscle_id_fk",
          "tableFrom": "exerciseToMuscle",
          "tableTo": "muscle",
          "columnsFrom": [
            "muscle_id"
          ],
          "columnsTo": [
            "id"
          ],
          "onDelete": "cascade",
          "onUpdate": "no action"
        }
      },
      "compositePrimaryKeys": {
        "exerciseToMuscle_exercise_id_muscle_id_pk": {
          "name": "exerciseToMuscle_exercise_id_muscle_id_pk",
          "columns": [
            "exercise_id",
            "muscle_id"
          ]
        }
      },
      "uniqueConstraints": {},
      "policies": {},
      "checkConstraints": {},
      "isRLSEnabled": false
    },
    "public.feedback": {
      "name": "feedback",
      "schema": "",
      "columns": {
        "id": {
          "name": "id",
          "type": "uuid",
          "primaryKey": true,
          "notNull": true,
          "default": "gen_random_uuid()"
        },
        "description": {
          "name": "description",
          "type": "text",
          "primaryKey": false,
          "notNull": true
        },
        "userId": {
          "name": "userId",
          "type": "uuid",
          "primaryKey": false,
          "notNull": false
        },
        "timestamp": {
          "name": "timestamp",
          "type": "timestamp",
          "primaryKey": false,
          "notNull": false,
          "default": "now()"
        },
        "url": {
          "name": "url",
          "type": "text",
          "primaryKey": false,
          "notNull": true
        },
        "type": {
          "name": "type",
          "type": "feedbackType",
          "typeSchema": "public",
          "primaryKey": false,
          "notNull": true,
          "default": "'other'"
        }
      },
      "indexes": {},
      "foreignKeys": {
        "feedback_userId_user_id_fk": {
          "name": "feedback_userId_user_id_fk",
          "tableFrom": "feedback",
          "tableTo": "user",
          "columnsFrom": [
            "userId"
          ],
          "columnsTo": [
            "id"
          ],
          "onDelete": "set null",
          "onUpdate": "no action"
        }
      },
      "compositePrimaryKeys": {},
      "uniqueConstraints": {},
      "policies": {},
      "checkConstraints": {},
      "isRLSEnabled": false
    },
    "public.friendRequestNotification": {
      "name": "friendRequestNotification",
      "schema": "",
      "columns": {
        "notificationId": {
          "name": "notificationId",
          "type": "uuid",
          "primaryKey": false,
          "notNull": true
        },
        "friendRequestId": {
          "name": "friendRequestId",
          "type": "uuid",
          "primaryKey": false,
          "notNull": true
        }
      },
      "indexes": {},
      "foreignKeys": {
        "friendRequestNotification_notificationId_notification_id_fk": {
          "name": "friendRequestNotification_notificationId_notification_id_fk",
          "tableFrom": "friendRequestNotification",
          "tableTo": "notification",
          "columnsFrom": [
            "notificationId"
          ],
          "columnsTo": [
            "id"
          ],
          "onDelete": "cascade",
          "onUpdate": "no action"
        },
        "friendRequestNotification_friendRequestId_friendRequest_id_fk": {
          "name": "friendRequestNotification_friendRequestId_friendRequest_id_fk",
          "tableFrom": "friendRequestNotification",
          "tableTo": "friendRequest",
          "columnsFrom": [
            "friendRequestId"
          ],
          "columnsTo": [
            "id"
          ],
          "onDelete": "cascade",
          "onUpdate": "no action"
        }
      },
      "compositePrimaryKeys": {},
      "uniqueConstraints": {},
      "policies": {},
      "checkConstraints": {},
      "isRLSEnabled": false
    },
    "public.notification": {
      "name": "notification",
      "schema": "",
      "columns": {
        "id": {
          "name": "id",
          "type": "uuid",
          "primaryKey": true,
          "notNull": true,
          "default": "gen_random_uuid()"
        },
        "createdAt": {
          "name": "createdAt",
          "type": "timestamp",
          "primaryKey": false,
          "notNull": true,
          "default": "now()"
        },
        "readAt": {
          "name": "readAt",
          "type": "timestamp",
          "primaryKey": false,
          "notNull": false
        },
        "hidden": {
          "name": "hidden",
          "type": "boolean",
          "primaryKey": false,
          "notNull": false,
          "default": false
        },
        "userId": {
          "name": "userId",
          "type": "uuid",
          "primaryKey": false,
          "notNull": true
        }
      },
      "indexes": {},
      "foreignKeys": {
        "notification_userId_user_id_fk": {
          "name": "notification_userId_user_id_fk",
          "tableFrom": "notification",
          "tableTo": "user",
          "columnsFrom": [
            "userId"
          ],
          "columnsTo": [
            "id"
          ],
          "onDelete": "cascade",
          "onUpdate": "no action"
        }
      },
      "compositePrimaryKeys": {},
      "uniqueConstraints": {},
      "policies": {},
      "checkConstraints": {},
      "isRLSEnabled": false
    },
    "public.workoutReviewNotification": {
      "name": "workoutReviewNotification",
      "schema": "",
      "columns": {
        "notificationId": {
          "name": "notificationId",
          "type": "uuid",
          "primaryKey": false,
          "notNull": true
        },
        "workoutReviewId": {
          "name": "workoutReviewId",
          "type": "uuid",
          "primaryKey": false,
          "notNull": true
        }
      },
      "indexes": {},
      "foreignKeys": {
        "workoutReviewNotification_notificationId_notification_id_fk": {
          "name": "workoutReviewNotification_notificationId_notification_id_fk",
          "tableFrom": "workoutReviewNotification",
          "tableTo": "notification",
          "columnsFrom": [
            "notificationId"
          ],
          "columnsTo": [
            "id"
          ],
          "onDelete": "cascade",
          "onUpdate": "no action"
        },
        "workoutReviewNotification_workoutReviewId_workoutReview_id_fk": {
          "name": "workoutReviewNotification_workoutReviewId_workoutReview_id_fk",
          "tableFrom": "workoutReviewNotification",
          "tableTo": "workoutReview",
          "columnsFrom": [
            "workoutReviewId"
          ],
          "columnsTo": [
            "id"
          ],
          "onDelete": "cascade",
          "onUpdate": "no action"
        }
      },
      "compositePrimaryKeys": {},
      "uniqueConstraints": {},
      "policies": {},
      "checkConstraints": {},
      "isRLSEnabled": false
    },
    "public.account": {
      "name": "account",
      "schema": "",
      "columns": {
        "userId": {
          "name": "userId",
          "type": "uuid",
          "primaryKey": false,
          "notNull": true
        },
        "type": {
          "name": "type",
          "type": "varchar(255)",
          "primaryKey": false,
          "notNull": true
        },
        "provider": {
          "name": "provider",
          "type": "varchar(255)",
          "primaryKey": false,
          "notNull": true
        },
        "providerAccountId": {
          "name": "providerAccountId",
          "type": "varchar(255)",
          "primaryKey": false,
          "notNull": true
        },
        "refresh_token": {
          "name": "refresh_token",
          "type": "text",
          "primaryKey": false,
          "notNull": false
        },
        "access_token": {
          "name": "access_token",
          "type": "text",
          "primaryKey": false,
          "notNull": false
        },
        "expires_at": {
          "name": "expires_at",
          "type": "integer",
          "primaryKey": false,
          "notNull": false
        },
        "token_type": {
          "name": "token_type",
          "type": "varchar(255)",
          "primaryKey": false,
          "notNull": false
        },
        "scope": {
          "name": "scope",
          "type": "varchar(255)",
          "primaryKey": false,
          "notNull": false
        },
        "id_token": {
          "name": "id_token",
          "type": "text",
          "primaryKey": false,
          "notNull": false
        },
        "session_state": {
          "name": "session_state",
          "type": "varchar(255)",
          "primaryKey": false,
          "notNull": false
        }
      },
      "indexes": {
        "account_userId_idx": {
          "name": "account_userId_idx",
          "columns": [
            {
              "expression": "userId",
              "isExpression": false,
              "asc": true,
              "nulls": "last"
            }
          ],
          "isUnique": false,
          "concurrently": false,
          "method": "btree",
          "with": {}
        }
      },
      "foreignKeys": {
        "account_userId_user_id_fk": {
          "name": "account_userId_user_id_fk",
          "tableFrom": "account",
          "tableTo": "user",
          "columnsFrom": [
            "userId"
          ],
          "columnsTo": [
            "id"
          ],
          "onDelete": "cascade",
          "onUpdate": "no action"
        }
      },
      "compositePrimaryKeys": {
        "account_provider_providerAccountId_pk": {
          "name": "account_provider_providerAccountId_pk",
          "columns": [
            "provider",
            "providerAccountId"
          ]
        }
      },
      "uniqueConstraints": {},
      "policies": {},
      "checkConstraints": {},
      "isRLSEnabled": false
    },
    "public.friendRequest": {
      "name": "friendRequest",
      "schema": "",
      "columns": {
        "id": {
          "name": "id",
          "type": "uuid",
          "primaryKey": true,
          "notNull": true,
          "default": "gen_random_uuid()"
        },
        "fromUserId": {
          "name": "fromUserId",
          "type": "uuid",
          "primaryKey": false,
          "notNull": true
        },
        "toUserId": {
          "name": "toUserId",
          "type": "uuid",
          "primaryKey": false,
          "notNull": true
        },
        "accepted": {
          "name": "accepted",
          "type": "boolean",
          "primaryKey": false,
          "notNull": false,
          "default": false
        },
        "ignored": {
          "name": "ignored",
          "type": "boolean",
          "primaryKey": false,
          "notNull": false,
          "default": false
        }
      },
      "indexes": {},
      "foreignKeys": {
        "friendRequest_fromUserId_user_id_fk": {
          "name": "friendRequest_fromUserId_user_id_fk",
          "tableFrom": "friendRequest",
          "tableTo": "user",
          "columnsFrom": [
            "fromUserId"
          ],
          "columnsTo": [
            "id"
          ],
          "onDelete": "cascade",
          "onUpdate": "no action"
        },
        "friendRequest_toUserId_user_id_fk": {
          "name": "friendRequest_toUserId_user_id_fk",
          "tableFrom": "friendRequest",
          "tableTo": "user",
          "columnsFrom": [
            "toUserId"
          ],
          "columnsTo": [
            "id"
          ],
          "onDelete": "cascade",
          "onUpdate": "no action"
        }
      },
      "compositePrimaryKeys": {},
      "uniqueConstraints": {},
      "policies": {},
      "checkConstraints": {},
      "isRLSEnabled": false
    },
    "public.friendShip": {
      "name": "friendShip",
      "schema": "",
      "columns": {
        "createdAt": {
          "name": "createdAt",
          "type": "timestamp",
          "primaryKey": false,
          "notNull": true,
          "default": "now()"
        },
        "userOne": {
          "name": "userOne",
          "type": "uuid",
          "primaryKey": false,
          "notNull": true
        },
        "userTwo": {
          "name": "userTwo",
          "type": "uuid",
          "primaryKey": false,
          "notNull": true
        }
      },
      "indexes": {},
      "foreignKeys": {
        "friendShip_userOne_user_id_fk": {
          "name": "friendShip_userOne_user_id_fk",
          "tableFrom": "friendShip",
          "tableTo": "user",
          "columnsFrom": [
            "userOne"
          ],
          "columnsTo": [
            "id"
          ],
          "onDelete": "cascade",
          "onUpdate": "no action"
        },
        "friendShip_userTwo_user_id_fk": {
          "name": "friendShip_userTwo_user_id_fk",
          "tableFrom": "friendShip",
          "tableTo": "user",
          "columnsFrom": [
            "userTwo"
          ],
          "columnsTo": [
            "id"
          ],
          "onDelete": "cascade",
          "onUpdate": "no action"
        }
      },
      "compositePrimaryKeys": {
        "friendShip_userOne_userTwo_pk": {
          "name": "friendShip_userOne_userTwo_pk",
          "columns": [
            "userOne",
            "userTwo"
          ]
        }
      },
      "uniqueConstraints": {},
      "policies": {},
      "checkConstraints": {},
      "isRLSEnabled": false
    },
    "public.session": {
      "name": "session",
      "schema": "",
      "columns": {
        "sessionToken": {
          "name": "sessionToken",
          "type": "text",
          "primaryKey": true,
          "notNull": true
        },
        "userId": {
          "name": "userId",
          "type": "uuid",
          "primaryKey": false,
          "notNull": true
        },
        "expires": {
          "name": "expires",
          "type": "timestamp with time zone",
          "primaryKey": false,
          "notNull": true
        }
      },
      "indexes": {
        "session_userId_idx": {
          "name": "session_userId_idx",
          "columns": [
            {
              "expression": "userId",
              "isExpression": false,
              "asc": true,
              "nulls": "last"
            }
          ],
          "isUnique": false,
          "concurrently": false,
          "method": "btree",
          "with": {}
        }
      },
      "foreignKeys": {
        "session_userId_user_id_fk": {
          "name": "session_userId_user_id_fk",
          "tableFrom": "session",
          "tableTo": "user",
          "columnsFrom": [
            "userId"
          ],
          "columnsTo": [
            "id"
          ],
          "onDelete": "cascade",
          "onUpdate": "no action"
        }
      },
      "compositePrimaryKeys": {},
      "uniqueConstraints": {},
      "policies": {},
      "checkConstraints": {},
      "isRLSEnabled": false
    },
    "public.userPrivateInformation": {
      "name": "userPrivateInformation",
      "schema": "",
      "columns": {
        "userId": {
          "name": "userId",
          "type": "uuid",
          "primaryKey": true,
          "notNull": true
        },
        "password": {
          "name": "password",
          "type": "varchar",
          "primaryKey": false,
          "notNull": false
        },
        "role": {
          "name": "role",
          "type": "userRole",
          "typeSchema": "public",
          "primaryKey": false,
          "notNull": true,
          "default": "'user'"
        }
      },
      "indexes": {},
      "foreignKeys": {
        "userPrivateInformation_userId_user_id_fk": {
          "name": "userPrivateInformation_userId_user_id_fk",
          "tableFrom": "userPrivateInformation",
          "tableTo": "user",
          "columnsFrom": [
            "userId"
          ],
          "columnsTo": [
            "id"
          ],
          "onDelete": "cascade",
          "onUpdate": "no action"
        }
      },
      "compositePrimaryKeys": {},
      "uniqueConstraints": {},
      "policies": {},
      "checkConstraints": {},
      "isRLSEnabled": false
    },
    "public.userProfile": {
      "name": "userProfile",
      "schema": "",
      "columns": {
        "userId": {
          "name": "userId",
          "type": "uuid",
          "primaryKey": true,
          "notNull": true
        },
        "selectedBadge": {
          "name": "selectedBadge",
          "type": "text",
          "primaryKey": false,
          "notNull": false
        }
      },
      "indexes": {},
      "foreignKeys": {
        "userProfile_userId_user_id_fk": {
          "name": "userProfile_userId_user_id_fk",
          "tableFrom": "userProfile",
          "tableTo": "user",
          "columnsFrom": [
            "userId"
          ],
          "columnsTo": [
            "id"
          ],
          "onDelete": "cascade",
          "onUpdate": "no action"
        },
        "userProfile_selectedBadge_badge_id_fk": {
          "name": "userProfile_selectedBadge_badge_id_fk",
          "tableFrom": "userProfile",
          "tableTo": "badge",
          "columnsFrom": [
            "selectedBadge"
          ],
          "columnsTo": [
            "id"
          ],
          "onDelete": "set null",
          "onUpdate": "no action"
        }
      },
      "compositePrimaryKeys": {},
      "uniqueConstraints": {},
      "policies": {},
      "checkConstraints": {},
      "isRLSEnabled": false
    },
    "public.userSettings": {
      "name": "userSettings",
      "schema": "",
      "columns": {
        "userId": {
          "name": "userId",
          "type": "uuid",
          "primaryKey": true,
          "notNull": true
        },
        "colorTheme": {
          "name": "colorTheme",
          "type": "varchar(20)",
          "primaryKey": false,
          "notNull": true
        },
        "borderRadius": {
          "name": "borderRadius",
          "type": "varchar(20)",
          "primaryKey": false,
          "notNull": true
        }
      },
      "indexes": {},
      "foreignKeys": {
        "userSettings_userId_user_id_fk": {
          "name": "userSettings_userId_user_id_fk",
          "tableFrom": "userSettings",
          "tableTo": "user",
          "columnsFrom": [
            "userId"
          ],
          "columnsTo": [
            "id"
          ],
          "onDelete": "cascade",
          "onUpdate": "no action"
        }
      },
      "compositePrimaryKeys": {},
      "uniqueConstraints": {},
      "policies": {},
      "checkConstraints": {},
      "isRLSEnabled": false
    },
    "public.user": {
      "name": "user",
      "schema": "",
      "columns": {
        "id": {
          "name": "id",
          "type": "uuid",
          "primaryKey": true,
          "notNull": true,
          "default": "gen_random_uuid()"
        },
        "name": {
          "name": "name",
          "type": "varchar(255)",
          "primaryKey": false,
          "notNull": false
        },
        "username": {
          "name": "username",
          "type": "varchar(20)",
          "primaryKey": false,
          "notNull": false
        },
        "email": {
          "name": "email",
          "type": "varchar(255)",
          "primaryKey": false,
          "notNull": true
        },
        "email_verified": {
          "name": "email_verified",
          "type": "timestamp with time zone",
          "primaryKey": false,
          "notNull": false,
          "default": "now()"
        },
        "image": {
          "name": "image",
          "type": "varchar(255)",
          "primaryKey": false,
          "notNull": false
        },
        "uploadedImage": {
          "name": "uploadedImage",
          "type": "varchar(255)",
          "primaryKey": false,
          "notNull": false
        }
      },
      "indexes": {},
      "foreignKeys": {},
      "compositePrimaryKeys": {},
      "uniqueConstraints": {
        "user_username_unique": {
          "name": "user_username_unique",
          "nullsNotDistinct": false,
          "columns": [
            "username"
          ]
        }
      },
      "policies": {},
      "checkConstraints": {},
      "isRLSEnabled": false
    },
    "public.verificationQueue": {
      "name": "verificationQueue",
      "schema": "",
      "columns": {
        "timeRequested": {
          "name": "timeRequested",
          "type": "timestamp with time zone",
          "primaryKey": false,
          "notNull": true,
          "default": "now()"
        },
        "token": {
          "name": "token",
          "type": "varchar",
          "primaryKey": false,
          "notNull": true
        },
        "email": {
          "name": "email",
          "type": "varchar",
          "primaryKey": false,
          "notNull": true
        }
      },
      "indexes": {},
      "foreignKeys": {},
      "compositePrimaryKeys": {},
      "uniqueConstraints": {
        "verificationQueue_token_unique": {
          "name": "verificationQueue_token_unique",
          "nullsNotDistinct": false,
          "columns": [
            "token"
          ]
        }
      },
      "policies": {},
      "checkConstraints": {},
      "isRLSEnabled": false
    },
    "public.verificationToken": {
      "name": "verificationToken",
      "schema": "",
      "columns": {
        "identifier": {
          "name": "identifier",
          "type": "text",
          "primaryKey": false,
          "notNull": true
        },
        "token": {
          "name": "token",
          "type": "text",
          "primaryKey": false,
          "notNull": true
        },
        "expires": {
          "name": "expires",
          "type": "timestamp with time zone",
          "primaryKey": false,
          "notNull": true
        }
      },
      "indexes": {},
      "foreignKeys": {},
      "compositePrimaryKeys": {
        "verificationToken_identifier_token_pk": {
          "name": "verificationToken_identifier_token_pk",
          "columns": [
            "identifier",
            "token"
          ]
        }
      },
      "uniqueConstraints": {
        "verificationToken_identifier_unique": {
          "name": "verificationToken_identifier_unique",
          "nullsNotDistinct": false,
          "columns": [
            "identifier"
          ]
        }
      },
      "policies": {},
      "checkConstraints": {},
      "isRLSEnabled": false
    },
    "public.waitlist": {
      "name": "waitlist",
      "schema": "",
      "columns": {
        "email": {
          "name": "email",
          "type": "varchar(255)",
          "primaryKey": true,
          "notNull": true
        },
        "timeSubmitted": {
          "name": "timeSubmitted",
          "type": "timestamp with time zone",
          "primaryKey": false,
          "notNull": true,
          "default": "now()"
        }
      },
      "indexes": {},
      "foreignKeys": {},
      "compositePrimaryKeys": {},
      "uniqueConstraints": {
        "waitlist_email_unique": {
          "name": "waitlist_email_unique",
          "nullsNotDistinct": false,
          "columns": [
            "email"
          ]
        }
      },
      "policies": {},
      "checkConstraints": {},
      "isRLSEnabled": false
    },
    "public.workout": {
      "name": "workout",
      "schema": "",
      "columns": {
        "id": {
          "name": "id",
          "type": "uuid",
          "primaryKey": true,
          "notNull": true,
          "default": "gen_random_uuid()"
        },
        "name": {
          "name": "name",
          "type": "text",
          "primaryKey": false,
          "notNull": true
        },
        "description": {
          "name": "description",
          "type": "text",
          "primaryKey": false,
          "notNull": true
        },
        "category": {
          "name": "category",
          "type": "text",
          "primaryKey": false,
          "notNull": true
        },
        "isPublic": {
          "name": "isPublic",
          "type": "boolean",
          "primaryKey": false,
          "notNull": true
        },
        "userId": {
          "name": "userId",
          "type": "uuid",
          "primaryKey": false,
          "notNull": true
        }
      },
      "indexes": {},
      "foreignKeys": {
        "workout_userId_user_id_fk": {
          "name": "workout_userId_user_id_fk",
          "tableFrom": "workout",
          "tableTo": "user",
          "columnsFrom": [
            "userId"
          ],
          "columnsTo": [
            "id"
          ],
          "onDelete": "cascade",
          "onUpdate": "no action"
        }
      },
      "compositePrimaryKeys": {},
      "uniqueConstraints": {},
      "policies": {},
      "checkConstraints": {},
      "isRLSEnabled": false
    },
    "public.workoutReview": {
      "name": "workoutReview",
      "schema": "",
      "columns": {
        "id": {
          "name": "id",
          "type": "uuid",
          "primaryKey": true,
          "notNull": true,
          "default": "gen_random_uuid()"
        },
        "createdAt": {
          "name": "createdAt",
          "type": "date",
          "primaryKey": false,
          "notNull": true
        },
        "editedAt": {
          "name": "editedAt",
          "type": "date",
          "primaryKey": false,
          "notNull": false
        },
        "userId": {
          "name": "userId",
          "type": "uuid",
          "primaryKey": false,
          "notNull": true
        },
        "workoutId": {
          "name": "workoutId",
          "type": "uuid",
          "primaryKey": false,
          "notNull": true
        },
        "rating": {
          "name": "rating",
          "type": "rating",
          "typeSchema": "public",
          "primaryKey": false,
          "notNull": true,
          "default": "'3'"
        },
        "comment": {
          "name": "comment",
          "type": "text",
          "primaryKey": false,
          "notNull": true
        }
      },
      "indexes": {},
      "foreignKeys": {
        "workoutReview_userId_user_id_fk": {
          "name": "workoutReview_userId_user_id_fk",
          "tableFrom": "workoutReview",
          "tableTo": "user",
          "columnsFrom": [
            "userId"
          ],
          "columnsTo": [
            "id"
          ],
          "onDelete": "cascade",
          "onUpdate": "no action"
        },
        "workoutReview_workoutId_workout_id_fk": {
          "name": "workoutReview_workoutId_workout_id_fk",
          "tableFrom": "workoutReview",
          "tableTo": "workout",
          "columnsFrom": [
            "workoutId"
          ],
          "columnsTo": [
            "id"
          ],
          "onDelete": "cascade",
          "onUpdate": "no action"
        }
      },
      "compositePrimaryKeys": {},
      "uniqueConstraints": {},
      "policies": {},
      "checkConstraints": {},
      "isRLSEnabled": false
    },
    "public.workoutSession": {
      "name": "workoutSession",
      "schema": "",
      "columns": {
        "id": {
          "name": "id",
          "type": "uuid",
          "primaryKey": true,
          "notNull": true,
          "default": "gen_random_uuid()"
        },
        "userId": {
          "name": "userId",
          "type": "uuid",
          "primaryKey": false,
          "notNull": true
        },
        "workoutId": {
          "name": "workoutId",
          "type": "uuid",
          "primaryKey": false,
          "notNull": true
        },
        "startedAt": {
          "name": "startedAt",
          "type": "timestamp",
          "primaryKey": false,
          "notNull": true,
          "default": "now()"
        },
        "endedAt": {
          "name": "endedAt",
          "type": "timestamp",
          "primaryKey": false,
          "notNull": false
        }
      },
      "indexes": {},
      "foreignKeys": {
        "workoutSession_userId_user_id_fk": {
          "name": "workoutSession_userId_user_id_fk",
          "tableFrom": "workoutSession",
          "tableTo": "user",
          "columnsFrom": [
            "userId"
          ],
          "columnsTo": [
            "id"
          ],
          "onDelete": "cascade",
          "onUpdate": "no action"
        },
        "workoutSession_workoutId_workout_id_fk": {
          "name": "workoutSession_workoutId_workout_id_fk",
          "tableFrom": "workoutSession",
          "tableTo": "workout",
          "columnsFrom": [
            "workoutId"
          ],
          "columnsTo": [
            "id"
          ],
          "onDelete": "set null",
          "onUpdate": "no action"
        }
      },
      "compositePrimaryKeys": {},
      "uniqueConstraints": {},
      "policies": {},
      "checkConstraints": {},
      "isRLSEnabled": false
    },
    "public.workoutSessionLog": {
      "name": "workoutSessionLog",
      "schema": "",
      "columns": {
        "id": {
          "name": "id",
          "type": "uuid",
          "primaryKey": true,
          "notNull": true,
          "default": "gen_random_uuid()"
        },
        "order": {
          "name": "order",
          "type": "integer",
          "primaryKey": false,
          "notNull": true
        },
        "workoutSessionId": {
          "name": "workoutSessionId",
          "type": "uuid",
          "primaryKey": false,
          "notNull": true
        },
        "exerciseId": {
          "name": "exerciseId",
          "type": "uuid",
          "primaryKey": false,
          "notNull": true
        },
        "startedAt": {
          "name": "startedAt",
          "type": "timestamp",
          "primaryKey": false,
          "notNull": false
        },
        "endedAt": {
          "name": "endedAt",
          "type": "timestamp",
          "primaryKey": false,
          "notNull": false
        }
      },
      "indexes": {},
      "foreignKeys": {
        "workoutSessionLog_workoutSessionId_workoutSession_id_fk": {
          "name": "workoutSessionLog_workoutSessionId_workoutSession_id_fk",
          "tableFrom": "workoutSessionLog",
          "tableTo": "workoutSession",
          "columnsFrom": [
            "workoutSessionId"
          ],
          "columnsTo": [
            "id"
          ],
          "onDelete": "cascade",
          "onUpdate": "no action"
        },
        "workoutSessionLog_exerciseId_exercise_id_fk": {
          "name": "workoutSessionLog_exerciseId_exercise_id_fk",
          "tableFrom": "workoutSessionLog",
          "tableTo": "exercise",
          "columnsFrom": [
            "exerciseId"
          ],
          "columnsTo": [
            "id"
          ],
          "onDelete": "set null",
          "onUpdate": "no action"
        }
      },
      "compositePrimaryKeys": {},
      "uniqueConstraints": {},
      "policies": {},
      "checkConstraints": {},
      "isRLSEnabled": false
    },
    "public.workoutSessionLogFragment": {
      "name": "workoutSessionLogFragment",
      "schema": "",
      "columns": {
        "id": {
          "name": "id",
          "type": "uuid",
          "primaryKey": true,
          "notNull": true,
          "default": "gen_random_uuid()"
        },
        "order": {
          "name": "order",
          "type": "integer",
          "primaryKey": false,
          "notNull": true
        },
        "workoutSessionLogId": {
          "name": "workoutSessionLogId",
          "type": "uuid",
          "primaryKey": false,
          "notNull": true
        },
        "reps": {
          "name": "reps",
          "type": "integer",
          "primaryKey": false,
          "notNull": true
        },
        "weight": {
          "name": "weight",
          "type": "integer",
          "primaryKey": false,
          "notNull": true
        },
        "duration": {
          "name": "duration",
          "type": "integer",
          "primaryKey": false,
          "notNull": true
        },
        "startedAt": {
          "name": "startedAt",
          "type": "timestamp",
          "primaryKey": false,
          "notNull": false
        },
        "endedAt": {
          "name": "endedAt",
          "type": "timestamp",
          "primaryKey": false,
          "notNull": false
        }
      },
      "indexes": {},
      "foreignKeys": {
        "workoutSessionLogFragment_workoutSessionLogId_workoutSessionLog_id_fk": {
          "name": "workoutSessionLogFragment_workoutSessionLogId_workoutSessionLog_id_fk",
          "tableFrom": "workoutSessionLogFragment",
          "tableTo": "workoutSessionLog",
          "columnsFrom": [
            "workoutSessionLogId"
          ],
          "columnsTo": [
            "id"
          ],
          "onDelete": "cascade",
          "onUpdate": "no action"
        }
      },
      "compositePrimaryKeys": {},
      "uniqueConstraints": {},
      "policies": {},
      "checkConstraints": {},
      "isRLSEnabled": false
    },
    "public.workoutSet": {
      "name": "workoutSet",
      "schema": "",
      "columns": {
        "id": {
          "name": "id",
          "type": "uuid",
          "primaryKey": true,
          "notNull": true,
          "default": "gen_random_uuid()"
        },
        "workoutId": {
          "name": "workoutId",
          "type": "uuid",
          "primaryKey": false,
          "notNull": true
        },
        "order": {
          "name": "order",
          "type": "integer",
          "primaryKey": false,
          "notNull": true
        }
      },
      "indexes": {},
      "foreignKeys": {
        "workoutSet_workoutId_workout_id_fk": {
          "name": "workoutSet_workoutId_workout_id_fk",
          "tableFrom": "workoutSet",
          "tableTo": "workout",
          "columnsFrom": [
            "workoutId"
          ],
          "columnsTo": [
            "id"
          ],
          "onDelete": "cascade",
          "onUpdate": "no action"
        }
      },
      "compositePrimaryKeys": {},
      "uniqueConstraints": {},
      "policies": {},
      "checkConstraints": {},
      "isRLSEnabled": false
    },
    "public.workoutSetCollection": {
      "name": "workoutSetCollection",
      "schema": "",
      "columns": {
        "id": {
          "name": "id",
          "type": "uuid",
          "primaryKey": true,
          "notNull": true,
          "default": "gen_random_uuid()"
        },
        "exerciseId": {
          "name": "exerciseId",
          "type": "uuid",
          "primaryKey": false,
          "notNull": true
        },
        "workoutSetId": {
          "name": "workoutSetId",
          "type": "uuid",
          "primaryKey": false,
          "notNull": true
        },
        "weight": {
          "name": "weight",
          "type": "integer[]",
          "primaryKey": false,
          "notNull": true
        },
        "reps": {
          "name": "reps",
          "type": "integer[]",
          "primaryKey": false,
          "notNull": true
        },
        "restTime": {
          "name": "restTime",
          "type": "integer[]",
          "primaryKey": false,
          "notNull": true
        },
        "duration": {
          "name": "duration",
          "type": "integer[]",
          "primaryKey": false,
          "notNull": true
        },
        "order": {
          "name": "order",
          "type": "integer",
          "primaryKey": false,
          "notNull": true
        }
      },
      "indexes": {},
      "foreignKeys": {
        "workoutSetCollection_exerciseId_exercise_id_fk": {
          "name": "workoutSetCollection_exerciseId_exercise_id_fk",
          "tableFrom": "workoutSetCollection",
          "tableTo": "exercise",
          "columnsFrom": [
            "exerciseId"
          ],
          "columnsTo": [
            "id"
          ],
          "onDelete": "cascade",
          "onUpdate": "no action"
        },
        "workoutSetCollection_workoutSetId_workoutSet_id_fk": {
          "name": "workoutSetCollection_workoutSetId_workoutSet_id_fk",
          "tableFrom": "workoutSetCollection",
          "tableTo": "workoutSet",
          "columnsFrom": [
            "workoutSetId"
          ],
          "columnsTo": [
            "id"
          ],
          "onDelete": "cascade",
          "onUpdate": "no action"
        }
      },
      "compositePrimaryKeys": {},
      "uniqueConstraints": {},
      "policies": {},
      "checkConstraints": {},
      "isRLSEnabled": false
    },
    "public.workoutToUser": {
      "name": "workoutToUser",
      "schema": "",
      "columns": {
        "userId": {
          "name": "userId",
          "type": "uuid",
          "primaryKey": false,
          "notNull": true
        },
        "workoutId": {
          "name": "workoutId",
          "type": "uuid",
          "primaryKey": false,
          "notNull": true
        }
      },
      "indexes": {},
      "foreignKeys": {
        "workoutToUser_userId_user_id_fk": {
          "name": "workoutToUser_userId_user_id_fk",
          "tableFrom": "workoutToUser",
          "tableTo": "user",
          "columnsFrom": [
            "userId"
          ],
          "columnsTo": [
            "id"
          ],
          "onDelete": "cascade",
          "onUpdate": "no action"
        },
        "workoutToUser_workoutId_workout_id_fk": {
          "name": "workoutToUser_workoutId_workout_id_fk",
          "tableFrom": "workoutToUser",
          "tableTo": "workout",
          "columnsFrom": [
            "workoutId"
          ],
          "columnsTo": [
            "id"
          ],
          "onDelete": "cascade",
          "onUpdate": "no action"
        }
      },
      "compositePrimaryKeys": {
        "workoutToUser_userId_workoutId_pk": {
          "name": "workoutToUser_userId_workoutId_pk",
          "columns": [
            "userId",
            "workoutId"
          ]
        }
      },
      "uniqueConstraints": {},
      "policies": {},
      "checkConstraints": {},
      "isRLSEnabled": false
    }
  },
  "enums": {
    "public.feedbackType": {
      "name": "feedbackType",
      "schema": "public",
      "values": [
        "bug",
        "feature",
        "improvement",
        "other"
      ]
    },
    "public.userRole": {
      "name": "userRole",
      "schema": "public",
      "values": [
        "superAdmin",
        "admin",
        "user"
      ]
    },
    "public.rating": {
      "name": "rating",
      "schema": "public",
      "values": [
        "1",
        "2",
        "3",
        "4",
        "5"
      ]
    }
  },
  "schemas": {},
  "sequences": {},
  "roles": {},
  "policies": {},
  "views": {},
  "_meta": {
    "columns": {},
    "schemas": {},
    "tables": {}
  }
}